odoo/addons/shopfloor_workstation_label_printer/README.rst
odoo/addons/shopfloor_workstation_label_printer/__init__.py
odoo/addons/shopfloor_workstation_label_printer/__manifest__.py
odoo/addons/shopfloor_workstation_label_printer/i18n/shopfloor_workstation_label_printer.pot
odoo/addons/shopfloor_workstation_label_printer/models/__init__.py
odoo/addons/shopfloor_workstation_label_printer/models/res_users.py
odoo/addons/shopfloor_workstation_label_printer/models/shopfloor_workstation.py
odoo/addons/shopfloor_workstation_label_printer/readme/CONTRIBUTORS.rst
odoo/addons/shopfloor_workstation_label_printer/readme/DESCRIPTION.rst
odoo/addons/shopfloor_workstation_label_printer/static/description/icon.png
odoo/addons/shopfloor_workstation_label_printer/static/description/index.html
odoo/addons/shopfloor_workstation_label_printer/views/res_users.xml
odoo/addons/shopfloor_workstation_label_printer/views/shopfloor_workstation.xml
odoo14_addon_shopfloor_workstation_label_printer-14.0.1.1.0.dist-info/METADATA
odoo14_addon_shopfloor_workstation_label_printer-14.0.1.1.0.dist-info/WHEEL
odoo14_addon_shopfloor_workstation_label_printer-14.0.1.1.0.dist-info/top_level.txt
odoo14_addon_shopfloor_workstation_label_printer-14.0.1.1.0.dist-info/RECORD
